telemc/__init__.py
telemc/controller.py
telemc/recorder.py
telemc/telemc.py
tests/__init__.py
tests/testutil.py
tests/telemc/__init__.py
tests/telemc/test_recorder.py
telemc-0.3.0.dist-info/METADATA
telemc-0.3.0.dist-info/WHEEL
telemc-0.3.0.dist-info/top_level.txt
telemc-0.3.0.dist-info/RECORD
