Metadata-Version: 2.1
Name: telemc
Version: 0.3.0
Summary: Python library for accessing telemd monitoring data
Home-page: https://github.com/edgerun/telemc-py
Author: Thomas Rausch
Author-email: t.rausch@dsg.tuwien.ac.at
License: UNKNOWN
Platform: UNKNOWN
Classifier: Programming Language :: Python :: 3
Classifier: Operating System :: OS Independent
Requires-Dist: redis (>=3.2.1)
